UNIngPy/UNIngPy.py
UNIngPy/__init__.py
UNIngPy-0.4.11.dist-info/LICENSE
UNIngPy-0.4.11.dist-info/METADATA
UNIngPy-0.4.11.dist-info/WHEEL
UNIngPy-0.4.11.dist-info/top_level.txt
UNIngPy-0.4.11.dist-info/RECORD
