Metadata-Version: 2.1
Name: UNIngPy
Version: 0.4.11
Summary: API para obtener articulos de la pagina oficial de la UNI Nicaragua
Home-page: https://github.com/MrH0wl/UNIngPy
Author: MrH0wl
Author-email: secmare@protonmail.com
License: UNKNOWN
Keywords: UNI Nicaragua,uni.edu.ni,UNI API,UNI-RUACS,Uni ruacs,Articulos UNI
Platform: UNKNOWN
